hPickle/__init__.py
py_hPickle-1.0.0.dist-info/LICENSE
py_hPickle-1.0.0.dist-info/METADATA
py_hPickle-1.0.0.dist-info/WHEEL
py_hPickle-1.0.0.dist-info/top_level.txt
py_hPickle-1.0.0.dist-info/RECORD
